README.txt
setup.cfg
setup.py
src/standardenum/__init__.py
src/standardenum/test_it.py
src/standardenum.egg-info/PKG-INFO
src/standardenum.egg-info/SOURCES.txt
src/standardenum.egg-info/dependency_links.txt
src/standardenum.egg-info/entry_points.txt
src/standardenum.egg-info/not-zip-safe
src/standardenum.egg-info/top_level.txt