Metadata-Version: 1.1
Name: standardenum
Version: 0.1
Summary: enum type
Home-page: https://bitbucket.org/aodag/standardenum
Author: Atsushi Odagiri
Author-email: aodagx@gmail.com
License: MIT
Platform: UNKNOWN
Classifier: Development Status :: 5 - Production/Stable
Classifier: Programming Language :: Python :: 2.7
Classifier: Programming Language :: Python :: 3
Classifier: Programming Language :: Python :: 3.2
Classifier: Topic :: Utilities
